cascader/__init__.py
cascader-0.0.dist-info/LICENSE
cascader-0.0.dist-info/METADATA
cascader-0.0.dist-info/WHEEL
cascader-0.0.dist-info/top_level.txt
cascader-0.0.dist-info/RECORD
