Metadata-Version: 2.1
Name: cascader
Version: 0.0
Summary: Infer the diffusion of retweet cascades on Twitter.
Home-page: https://github.com/mr-devs/cascader
Download-URL: https://pypi.org/project/cascader/
Author: Matthew DeVerna
Author-email: mdeverna@iu.edu
License: MIT
Project-URL: Documentation, https://github.com/mr-devs/cascader
Project-URL: Issue Tracker, https://github.com/mr-devs/cascader/issues
Project-URL: Source Code, https://github.com/mr-devs/cascader
Requires-Python: >=3.7
License-File: LICENSE
Requires-Dist: numpy (>=1.21.6)
Requires-Dist: pandas (>=1.2.4)
